Workbook

Sheet Parametres
A1: Paramètre | B1: Valeur | C1: Description
A2: Devise | B2: MAD | C2: Devise d'analyse
A3: Année_Analyse | B3: 2024 | C3: Année principale
A4: Seuil_Alerte_Cash | B4: 20000 | C4: Minimum trésorerie (MAD)
A5: TVA_% | B5: 20% | C5: TVA applicable
A6: Objectif_CA_Mensuel | B6: 50000 | C6: Objectif CA/mois (MAD)
A7: Objectif_Cash_Mensuel | B7: 40000 | C7: Objectif cash/mois (MAD)

Sheet Ventes
A1: Date_Facture | B1: Invoice_ID | C1: Client | D1: Produit | E1: Quantite | F1: Prix_Unitaire | G1: Montant_HT | H1: TVA | I1: Montant_TTC | J1: Date_Paiement_Prevue | K1: Date_Paiement_Reelle | L1: Statut_Paiement
A2: 44932 | B2: INV-001 | C2: Client E | D2: Design Graphique | E2: 1 | F2: 4000 | G2: =E2*F2 -> 4000 | H2: =G2*Parametres!B$5 -> 800 | I2: =G2+H2 -> 4800 | J2: 44958 | K2: 44961 | L2: Payé
A3: 44929 | B3: INV-002 | C3: Client F | D3: Shooting Photo | E3: 2 | F3: 8000 | G3: =E3*F3 -> 16000 | H3: =G3*Parametres!B$5 -> 3200 | I3: =G3+H3 -> 19200 | J3: 44951 | K3: 44948 | L3: Payé
A4: 44955 | B4: INV-003 | C4: Client E | D4: Montage Vidéo | E4: 1 | F4: 6000 | G4: =E4*F4 -> 6000 | H4: =G4*Parametres!B$5 -> 1200 | I4: =G4+H4 -> 7200 | J4: 44970 | K4: 44977 | L4: Payé (retard)
A5: 44930 | B5: INV-004 | C5: Client J | D5: Design Graphique | E5: 1 | F5: 5000 | G5: =E5*F5 -> 5000 | H5: =G5*Parametres!B$5 -> 1000 | I5: =G5+H5 -> 6000 | J5: 44955 | K5: 44953 | L5: Payé
A6: 44931 | B6: INV-005 | C6: Client I | D6: Design Graphique | E6: 2 | F6: 5000 | G6: =E6*F6 -> 10000 | H6: =G6*Parametres!B$5 -> 2000 | I6: =G6+H6 -> 12000 | J6: 44959 | K6: 44962 | L6: Payé
A7: 44976 | B7: INV-006 | C7: Client J | D7: Design Graphique | E7: 2 | F7: 5000 | G7: =E7*F7 -> 10000 | H7: =G7*Parametres!B$5 -> 2000 | I7: =G7+H7 -> 12000 | J7: 44992 | K7: 44994 | L7: Payé
A8: 44974 | B8: INV-007 | C8: Client E | D8: Montage Vidéo | E8: 2 | F8: 5000 | G8: =E8*F8 -> 10000 | H8: =G8*Parametres!B$5 -> 2000 | I8: =G8+H8 -> 12000 | J8: 44996 | K8: 45005 | L8: Payé (retard)
A9: 44980 | B9: INV-008 | C9: Client C | D9: Design Graphique | E9: 2 | F9: 3000 | G9: =E9*F9 -> 6000 | H9: =G9*Parametres!B$5 -> 1200 | I9: =G9+H9 -> 7200 | J9: 45001 | K9: 44997 | L9: Payé
A10: 44964 | B10: INV-009 | C10: Client D | D10: Shooting Photo | E10: 2 | F10: 11000 | G10: =E10*F10 -> 22000 | H10: =G10*Parametres!B$5 -> 4400 | I10: =G10+H10 -> 26400 | J10: 44993 | K10: 44995 | L10: Payé
A11: 44959 | B11: INV-010 | C11: Client H | D11: Design Graphique | E11: 2 | F11: 3000 | G11: =E11*F11 -> 6000 | H11: =G11*Parametres!B$5 -> 1200 | I11: =G11+H11 -> 7200 | J11: 44986 | K11: 44996 | L11: Payé (retard)
A12: 45004 | B12: INV-011 | C12: Client C | D12: Design Graphique | E12: 3 | F12: 5000 | G12: =E12*F12 -> 15000 | H12: =G12*Parametres!B$5 -> 3000 | I12: =G12+H12 -> 18000 | J12: 45026 | K12: 45028 | L12: Payé
A13: 45015 | B13: INV-012 | C13: Client E | D13: Design Graphique | E13: 1 | F13: 4000 | G13: =E13*F13 -> 4000 | H13: =G13*Parametres!B$5 -> 800 | I13: =G13+H13 -> 4800 | J13: 45038 | K13: 45047 | L13: Payé (retard)
... A115: 45563 | B115: INV-114 | C115: Client C | D115: Design Graphique | E115: 3 | F115: 5000 | G115: =E115*F115 -> 15000 | H115: =G115*Parametres!B$5 -> 3000 | I115: =G115+H115 -> 18000 | J115: 45586 | K115: 45584 | L115: Payé
A116: 45615 | B116: INV-115 | C116: Client J | D116: Montage Vidéo | E116: 2 | F116: 6000 | G116: =E116*F116 -> 12000 | H116: =G116*Parametres!B$5 -> 2400 | I116: =G116+H116 -> 14400 | J116: 45642 | L116: À venir
A117: 45591 | B117: INV-116 | C117: Client J | D117: Montage Vidéo | E117: 1 | F117: 4000 | G117: =E117*F117 -> 4000 | H117: =G117*Parametres!B$5 -> 800 | I117: =G117+H117 -> 4800 | J117: 45612 | K117: 45608 | L117: Payé
A118: 45608 | B118: INV-117 | C118: Client A | D118: Production Événementielle | E118: 1 | F118: 12000 | G118: =E118*F118 -> 12000 | H118: =G118*Parametres!B$5 -> 2400 | I118: =G118+H118 -> 14400 | J118: 45627 | L118: À venir
A119: 45601 | B119: INV-118 | C119: Client D | D119: Design Graphique | E119: 1 | F119: 4000 | G119: =E119*F119 -> 4000 | H119: =G119*Parametres!B$5 -> 800 | I119: =G119+H119 -> 4800 | J119: 45624 | L119: À venir
A120: 45603 | B120: INV-119 | C120: Client B | D120: Shooting Photo | E120: 2 | F120: 11000 | G120: =E120*F120 -> 22000 | H120: =G120*Parametres!B$5 -> 4400 | I120: =G120+H120 -> 26400 | J120: 45626 | L120: À venir
A121: 45603 | B121: INV-120 | C121: Client F | D121: Montage Vidéo | E121: 3 | F121: 5000 | G121: =E121*F121 -> 15000 | H121: =G121*Parametres!B$5 -> 3000 | I121: =G121+H121 -> 18000 | J121: 45633 | L121: À venir
A122: 45621 | B122: INV-121 | C122: Client B | D122: Montage Vidéo | E122: 3 | F122: 4000 | G122: =E122*F122 -> 12000 | H122: =G122*Parametres!B$5 -> 2400 | I122: =G122+H122 -> 14400 | J122: 45643 | L122: À venir
A123: 45631 | B123: INV-122 | C123: Client A | D123: Production Événementielle | E123: 2 | F123: 10000 | G123: =E123*F123 -> 20000 | H123: =G123*Parametres!B$5 -> 4000 | I123: =G123+H123 -> 24000 | J123: 45648 | L123: À venir
A124: 45625 | B124: INV-123 | C124: Client D | D124: Design Graphique | E124: 3 | F124: 5000 | G124: =E124*F124 -> 15000 | H124: =G124*Parametres!B$5 -> 3000 | I124: =G124+H124 -> 18000 | J124: 45640 | L124: À venir
A125: 45635 | B125: INV-124 | C125: Client H | D125: Design Graphique | E125: 3 | F125: 2000 | G125: =E125*F125 -> 6000 | H125: =G125*Parametres!B$5 -> 1200 | I125: =G125+H125 -> 7200 | J125: 45651 | L125: À venir
A126: 45635 | B126: INV-125 | C126: Client B | D126: Production Événementielle | E126: 3 | F126: 14000 | G126: =E126*F126 -> 42000 | H126: =G126*Parametres!B$5 -> 8400 | I126: =G126+H126 -> 50400 | J126: 45653 | L126: À venir
A127: 45634 | B127: INV-126 | C127: Client J | D127: Design Graphique | E127: 1 | F127: 3000 | G127: =E127*F127 -> 3000 | H127: =G127*Parametres!B$5 -> 600 | I127: =G127+H127 -> 3600 | J127: 45657 | L127: À venir

Sheet Depenses
A1: Date_Depense | B1: Expense_ID | C1: Fournisseur | D1: Type_Cout | E1: Categorie | F1: Description | G1: Montant | H1: Date_Paiement | I1: Statut_Paiement
A2: 44927 | B2: EXP-001 | C2: Propriétaire | D2: Fixe | E2: Loyer | F2: Location studio | G2: 3000 | H2: 44929 | I2: Payé
A3: 44927 | B3: EXP-002 | C3: Banque | D3: Fixe | E3: Salaires | F3: Salaire équipe | G3: 12000 | H3: 44931 | I3: Payé
A4: 44927 | B4: EXP-003 | C4: Assurance Pro | D4: Fixe | E4: Assurance | F4: Assurance professionnelle | G4: 800 | H4: 44930 | I4: Payé
A5: 44933 | B5: EXP-004 | C5: Fournisseur Matériel | D5: Variable | E5: Matériel | F5: Achat matériel | G5: 4474 | H5: 44936 | I5: Payé
A6: 44927 | B6: EXP-005 | C6: Propriétaire | D6: Fixe | E6: Loyer | F6: Location studio | G6: 3000 | H6: 44931 | I6: Payé
A7: 44927 | B7: EXP-006 | C7: Banque | D7: Fixe | E7: Salaires | F7: Salaire équipe | G7: 12000 | H7: 44930 | I7: Payé
A8: 44927 | B8: EXP-007 | C8: Assurance Pro | D8: Fixe | E8: Assurance | F8: Assurance professionnelle | G8: 800 | H8: 44928 | I8: Payé
A9: 44946 | B9: EXP-008 | C9: Freelance Monteur | D9: Variable | E9: Freelances | F9: Achat freelances | G9: 2570 | H9: 44949 | I9: Payé
A10: 44946 | B10: EXP-009 | C10: Freelance Monteur | D10: Variable | E10: Freelances | F10: Achat freelances | G10: 1740 | H10: 44946 | I10: Payé
A11: 44986 | B11: EXP-010 | C11: Propriétaire | D11: Fixe | E11: Loyer | F11: Location studio | G11: 3000 | H11: 44990 | I11: Payé
A12: 44986 | B12: EXP-011 | C12: Banque | D12: Fixe | E12: Salaires | F12: Salaire équipe | G12: 12000 | H12: 44986 | I12: Payé
A13: 44986 | B13: EXP-012 | C13: Assurance Pro | D13: Fixe | E13: Assurance | F13: Assurance professionnelle | G13: 800 | H13: 44990 | I13: Payé
... A108: 45606 | B108: EXP-107 | C108: Fournisseur Matériel | D108: Variable | E108: Matériel | F108: Achat matériel | G108: 3923 | H108: 45608 | I108: Payé

Sheet Cash_Flow
A1: Date | B1: CA_Facture | C1: Cash_Entrant_Reel | D1: Depenses_Facturees | E1: Cash_Sortant_Reel | F1: Solde_Cash
A2: NOTE: Cet onglet sera construit en détail dans le Thème 3

Sheet Dashboard_Excel
A1: DASHBOARD FINANCIER - NGROUP MEDIA & DIGITAL
A3: KPI | B3: Valeur | C3: Format
A4: CA Total | B4: =SUMIF(Ventes!G:G,">0") -> 2079000 | C4: =Parametres!B2 -> MAD | D4: → Somme de tous les montants HT des ventes
A5: Coûts Variables | B5: =SUMIFS(Depenses!G:G,Depenses!D:D,"Variable") -> 109083 | C5: =Parametres!B2 -> MAD | D5: → Somme des dépenses de type "Variable"
A6: Coûts Fixes | B6: =SUMIFS(Depenses!G:G,Depenses!D:D,"Fixe") -> 379200 | C6: =Parametres!B2 -> MAD | D6: → Somme des dépenses de type "Fixe"
A7: Marge Brute | B7: =B4-B5 -> 1969917 | C7: =Parametres!B2 -> MAD | D7: → CA - Coûts Variables
A8: Marge Brute % | B8: =B7/B4 -> 0.94753102 | D8: → Marge Brute / CA
A9: Bénéfice Net | B9: =B7-B6 -> 1590717 | C9: =Parametres!B2 -> MAD | D9: → Marge Brute - Coûts Fixes
A10: Marge Nette % | B10: =B9/B4 -> 0.76513564 | D10: → Bénéfice Net / CA
A13: NOTES:
A14: • Les formules utilisent des références directes aux onglets Ventes et Depenses
A15: • Les KPIs sont calculés sur l'ensemble de la période (24 mois)
A16: • Pour analyse par période, utiliser Power BI
